codegen_cli/call_tools.py
codegen_cli/conversation_memory.py
codegen_cli/main.py
codegen_cli/output.py
codegen_cli/repl.py
codegen_cli/tools_registry.py
codegen_cli/config/behavior.md
codegen_cli/config/system_prompt.md
codegen_cli/models/schema.py
codegen_cli/tools/bash.py
codegen_cli/tools/delete.py
codegen_cli/tools/edit.py
codegen_cli/tools/glob.py
codegen_cli/tools/grep.py
codegen_cli/tools/ls.py
codegen_cli/tools/multiedit.py
codegen_cli/tools/read.py
codegen_cli/tools/todowrite.py
codegen_cli/tools/webfetch.py
codegen_cli/tools/websearch.py
codegen_cli/tools/write.py
codegen_cli-0.5.0.dist-info/METADATA
codegen_cli-0.5.0.dist-info/WHEEL
codegen_cli-0.5.0.dist-info/entry_points.txt
codegen_cli-0.5.0.dist-info/licenses/LICENSE
codegen_cli-0.5.0.dist-info/RECORD
