Metadata-Version: 2.4
Name: codegen-cli
Version: 0.5.0
Summary: Command-line coding agent with iterative reasoning, inspired by Claude Code and Cursor CLI, powered by Google Gemini API.
Project-URL: Homepage, https://github.com/vaishnavip-23/CodeGen-CLI
Project-URL: Documentation, https://github.com/vaishnavip-23/CodeGen-CLI/blob/main/docs/README.md
Project-URL: Repository, https://github.com/vaishnavip-23/CodeGen-CLI
Author-email: CodeGen CLI Team <vaishnavipullakhandam@gmail.com>
Maintainer-email: CodeGen CLI Team <vaishnavipullakhandam@gmail.com>
License: MIT
License-File: LICENSE
Keywords: agent,ai,assistant,cli,code,coding,development,go,javascript,natural-language,programming,python,rust,universal
Classifier: Development Status :: 4 - Beta
Classifier: Intended Audience :: Developers
Classifier: License :: OSI Approved :: MIT License
Classifier: Operating System :: OS Independent
Classifier: Programming Language :: Python :: 3
Classifier: Programming Language :: Python :: 3.10
Classifier: Programming Language :: Python :: 3.11
Classifier: Programming Language :: Python :: 3.12
Classifier: Topic :: Software Development :: Libraries :: Python Modules
Classifier: Topic :: Text Processing :: General
Classifier: Topic :: Utilities
Requires-Python: >=3.10
Requires-Dist: beautifulsoup4>=4.13.5
Requires-Dist: google-genai<2.0.0,>=1.50.0
Requires-Dist: instructor>=1.0.0
Requires-Dist: pydantic>=2.10.0
Requires-Dist: python-dotenv>=1.1.0
Requires-Dist: requests>=2.32.0
Provides-Extra: dev
Requires-Dist: black>=23.0.0; extra == 'dev'
Requires-Dist: pytest-cov>=4.0.0; extra == 'dev'
Requires-Dist: pytest>=7.0.0; extra == 'dev'
